eemont/__init__.py
eemont/image.py
eemont/imagecollection.py
eemont-0.1.6.dist-info/LICENSE
eemont-0.1.6.dist-info/METADATA
eemont-0.1.6.dist-info/WHEEL
eemont-0.1.6.dist-info/top_level.txt
eemont-0.1.6.dist-info/RECORD
