Metadata-Version: 2.1
Name: eemont
Version: 0.1.6
Summary: A Python package that extends Google Earth Engine
Home-page: https://github.com/davemlz/eemont
Author: David Montero Loaiza
Author-email: dml.mont@gmail.com
License: MIT
Platform: UNKNOWN
Classifier: Development Status :: 2 - Pre-Alpha
Classifier: License :: OSI Approved :: MIT License
Classifier: Programming Language :: Python
Classifier: Programming Language :: Python :: 2
Classifier: Programming Language :: Python :: 2.7
Classifier: Programming Language :: Python :: 3
Classifier: Programming Language :: Python :: 3.4
Classifier: Programming Language :: Python :: 3.5
Classifier: Programming Language :: Python :: 3.6
Classifier: Programming Language :: Python :: 3.7
Requires-Dist: earthengine-api
Requires-Dist: numpy
